{
  "id": "10215",
  "title": "(x) Fossum Design - Times New Roman, TV Nord {Dav}",
  "forum": "Type ID Board [OLD]",
  "tags": [
    "Type ID Board [OLD]"
  ],
  "content": "I am trying to identify the 2 fonts used here. \"design\" looks like Sys, but \"g\" is different.   \n ![](http://web.archive.org/web/20150415043804im_/http:/www.typophile.com/forums/messages/83/69279.jpg)\n\n",
  "author": "designalchemy",
  "time": "10 Apr 2005 — 4:44am",
  "uid": "804",
  "comments": [
    {
      "time": "10 Apr 2005 — 5:05am",
      "content": "'fossum' seems to be ' [Times New Roman](http://web.archive.org/web/20150415043804/http:/www.fontshop.com/index.cfm?fuseaction=verity.search&font_categories_search=font_name_search&searchstr=Times+New+Roman)' _( Italic )_..   \n'design' should be ' [TV Nord](http://web.archive.org/web/20150415043804/http:/www.fontshop.com/index.cfm?fuseaction=verity.search&font_categories_search=font_name_search&searchstr=TV+Nord)' _( Condensed / 3 )_..\n\n"
    }
  ]
}
