{
  "id": "102233",
  "title": "What font is used in logo",
  "forum": "Type ID Board",
  "tags": [
    "Type ID Board"
  ],
  "content": "Hi!  \nCan anybody help me identifying this font:\n\n ![](http://web.archive.org/web/20130416001322im_/http:/typophile.com/files/BC_logo_5755.JPG)\n\nI found second line is \"Lekton\" font; any ideas on the other font (or is it custom?)? Thank you for your help!\n\n",
  "author": "Maas",
  "time": "12 Apr 2013 — 3:21am",
  "uid": "9328",
  "comments": [
    {
      "time": "12 Apr 2013 — 3:26am",
      "content": "[Velocity](http://web.archive.org/web/20130416001322/http:/www.dafont.com/velocity.font)\n\n"
    },
    {
      "time": "12 Apr 2013 — 3:41am",
      "content": "Thanks!\n\n"
    }
  ]
}
