{
  "id": "104367",
  "title": "Used Magazine",
  "forum": "Type ID Board [OLD]",
  "tags": [
    "Used Magazine",
    "Type ID Board [OLD]"
  ],
  "content": "Anyone know the font on this one (Young gods…)  \nReminded me a bit of both Radmi Peskos Larish Neue and Alias Harbour but it's neither.\n\n ![](http://web.archive.org/web/20140828205533im_/http:/typophile.com/files/Screen%20Shot%202013-07-05%20at%2010_4120.15.48%20AM.png)\n\n",
  "author": "SodaPopinski",
  "time": "5 Jul 2013 — 1:19am",
  "uid": "171854",
  "comments": [
    {
      "time": "5 Jul 2013 — 1:35am",
      "content": "Looks like [Stanley Poster](http://web.archive.org/web/20140828205533/http:/optimo.ch/typefaces_Stanley_Poster.html).\n\n"
    },
    {
      "time": "5 Jul 2013 — 1:54am",
      "content": "Thanks a lot Ryuk!\n\n"
    }
  ]
}
