{
  "id": "106210",
  "title": "A really familiar serif font",
  "forum": "Home",
  "tags": [
    "Serif"
  ],
  "content": " ![](http://web.archive.org/web/20140830012305im_/http:/typophile.com/files/%E3%82%B9%E3%82%AF%E3%83%AA%E3%83%BC%E3%83%B3%E3%82%B7%E3%83%A7%E3%83%83%E3%83%88%EF%BC%882011-09-10%202_6147.05.02%EF%BC%89.png)\n\n ![](http://web.archive.org/web/20140830012305im_/http:/typophile.com/files/forty-percent-against-rights_3862.png)\n\n ![](http://web.archive.org/web/20140830012305im_/http:/typophile.com/files/%E3%82%B9%E3%82%AF%E3%83%AA%E3%83%BC%E3%83%B3%E3%82%B7%E3%83%A7%E3%83%83%E3%83%88%EF%BC%882011-09-10%202_6217.04.18%EF%BC%89.png)\n\n ![](http://web.archive.org/web/20140830012305im_/http:/typophile.com/files/%E3%82%B9%E3%82%AF%E3%83%AA%E3%83%BC%E3%83%B3%E3%82%B7%E3%83%A7%E3%83%83%E3%83%88%EF%BC%882011-09-10%202_5997.04.51%EF%BC%89.png)\n\n ![](http://web.archive.org/web/20140830012305im_/http:/typophile.com/files/%E3%82%B9%E3%82%AF%E3%83%AA%E3%83%BC%E3%83%B3%E3%82%B7%E3%83%A7%E3%83%83%E3%83%88%EF%BC%882011-09-10%202_6432.05.23%EF%BC%89.png)\n\n ![](http://web.archive.org/web/20140830012305im_/http:/typophile.com/files/d0d6e720c05aba1920b1d40a6b905594_5031.png)\n\n ![](http://web.archive.org/web/20140830012305im_/http:/typophile.com/files/1237101_10153239624805121_1819062493_n_5676.jpg)\n\n ![](http://web.archive.org/web/20140830012305im_/http:/typophile.com/files/64140_10153239633135121_565983798_n_3602.jpg)\n\n",
  "author": "al0212",
  "time": "10 Sep 2013 — 12:19am",
  "uid": "214537",
  "comments": [
    {
      "time": "10 Sep 2013 — 2:05am",
      "content": "NO WAY WE ARE GOING TO LOSE: [Caslon](http://web.archive.org/web/20140830012305/http:/www.myfonts.com/search/caslon)  \nF: [Century Old Style](http://web.archive.org/web/20140830012305/http:/www.myfonts.com/search/century+old+style) Bold  \nYou're irrelevant/Doubt everything: [Century Old Style](http://web.archive.org/web/20140830012305/http:/www.myfonts.com/search/century+old+style) Italic\n\n"
    }
  ]
}
