{
  "id": "113880",
  "title": "Illustrator and Layered Fonts",
  "forum": "General Discussions",
  "tags": [
    "Adobe Illustrator",
    "alignment",
    "display font",
    "General Discussions",
    "layered"
  ],
  "content": "I'm working on a layered font family and everything is great in InDesign, but the alignment is off by about 1 or 2 vertical points in Illustrator when I switch between styles. Does anyone know if this is normal?\n\nI'm a little nervous to release a font that doesn't \"line up\" in all programs.\n\n",
  "author": "jhilgert00",
  "time": "3 Feb 2014 — 10:56pm",
  "uid": "88560",
  "comments": [

  ]
}
