{
  "id": "114821",
  "title": "Honest Ed's sells its signs",
  "forum": "General Discussions",
  "tags": [
    "General Discussions",
    "hand painted signs",
    "sign painters",
    "signs"
  ],
  "content": "[http://www.cbc.ca/news/canada/toronto/honest-ed-s-sells-its-signs-1.2564...](http://web.archive.org/web/20150414181644/http:/www.cbc.ca/news/canada/toronto/honest-ed-s-sells-its-signs-1.2564440?cmp=rss \"http://www.cbc.ca/news/canada/toronto/honest-ed-s-sells-its-signs-1.2564440?cmp=rss\")\n\nHonest Ed's is a discount store and long time fixture in Downtown Toronto since 1948. http://en.wikipedia.org/wiki/Honest\\_Ed's  \nThey are closing now so someone can build - you guessed it, A condo.\n\nthey were one of the last places to employ sign painters to do their in-house signs and advertising.  \n [http://www.youtube.com/watch?v=hOrAeW7soVI](http://web.archive.org/web/20150414181644/http:/www.youtube.com/watch?v=hOrAeW7soVI \"http://www.youtube.com/watch?v=hOrAeW7soVI\")\n\n",
  "author": "russellm",
  "time": "7 Mar 2014 — 8:08pm",
  "uid": "13076",
  "comments": [
    {
      "time": "8 Mar 2014 — 6:12am",
      "content": "See also:  \n [https://vimeo.com/18646886](http://web.archive.org/web/20150414181644/https:/vimeo.com/18646886 \"https://vimeo.com/18646886\")\n\n"
    },
    {
      "time": "9 Mar 2014 — 5:57pm",
      "content": "thanks\n\n"
    }
  ]
}
