{
  "id": "115667",
  "title": "Please ID this serif used by Musikexpress.",
  "forum": "Home",
  "tags": [
    "Serif"
  ],
  "content": " ![](http://web.archive.org/web/20150419023514im_/http:/typophile.com/files/bild_5942.jpg)\n\nFont:&nbsp;\n\n Lyon Display Black \n\nSolved By:&nbsp;\n\n [R.](http://web.archive.org/web/20150419023514/http:/typophile.com/user/57325 \"View user profile.\")\n\n",
  "author": "Quadrato",
  "time": "10 Apr 2014 — 5:37am",
  "uid": "36191",
  "comments": [
    {
      "time": "10 Apr 2014 — 10:20am",
      "content": "This is [Lyon Display (Black)](http://web.archive.org/web/20150419023514/https:/commercialtype.com/typefaces/lyon/lyon_display).\n\n"
    },
    {
      "time": "10 Apr 2014 — 3:21pm",
      "content": "Thanks a lot, R.!\n\n"
    },
    {
      "time": "11 Apr 2014 — 2:20am",
      "content": "Glad to help. Lyon is a lovely typeface.\n\n"
    }
  ]
}
