{
  "id": "116393",
  "title": "Uppercase typeface with bigger first letters",
  "forum": "General Discussions",
  "tags": [
    "General Discussions"
  ],
  "content": "Hi, I was wondering is there a specific term for uppercase typefaces which have their first letters bigger? Thank you.\n\n",
  "author": "migle",
  "time": "9 May 2014 — 7:48am",
  "uid": "63972",
  "comments": [
    {
      "time": "9 May 2014 — 8:06am",
      "content": "Sorry for the post, I've figured out it already.\n\n"
    },
    {
      "time": "9 May 2014 — 10:03am",
      "content": "So ... is there a specific term? Or did you find out there isn't?\n\n"
    },
    {
      "time": "9 May 2014 — 10:24am",
      "content": "I think she may simply have had a different conceptualization of what we think of as small caps. The creativity of the human mind is cool. :)\n\n"
    }
  ]
}
