{
  "id": "15716",
  "title": "(x) Axon-Kitchenworks rounded tech sans - Storno {Ganesh (self)}",
  "forum": "Type ID Board",
  "tags": [

  ],
  "content": "In use on [www.axon-kitchenworks.com](http://web.archive.org/web/20080503010620/http:/www.axon-kitchenworks.com/ \"www.axon-kitchenworks.com\")  \nThanks\n\n| Attachment | Size |\n| --- | --- |\n| [Axon.jpg](http://web.archive.org/web/20080503010620/http:/typophile.com/files/Axon.jpg) | 60.03 KB |\n\n [‹ (x) system pixelfont ca.1988 - Atari ST bitmap face {Simon}](http://web.archive.org/web/20080503010620/http:/www.typophile.com/node/15713 \"Go to previous forum topic\") [Madonna logo on \"Confessions on a Dancefloor\" CD-cover ›](http://web.archive.org/web/20080503010620/http:/www.typophile.com/node/15719 \"Go to next forum topic\")\n\n",
  "author": "<a href=\"/web/20080503010620/http://www.typophile.com/user/3348\" title=\"View user profile.\">ganesh</a>",
  "time": "<br>",
  "uid": "3348",
  "comments": [
    {
      "time": " 18.Oct.2005 9.29am",
      "content": "....couple threads with this font, but no luck. maybe custom.\n\n"
    },
    {
      "time": " 18.Oct.2005 9.29am",
      "content": "Hi, this is a tricky one, discussed a few days before in here: [http://typophile.com/node/14859](http://web.archive.org/web/20080503010620/http:/typophile.com/node/14859 \"http://typophile.com/node/14859\").\n\nBetter luck for you...\n\nJorge Marcedo  \nCoimbra | Portugal\n\n"
    },
    {
      "time": " 18.Oct.2005 10.12am",
      "content": "It reminds me a face by Lineto, you can check [http://www.lineto.com](http://web.archive.org/web/20080503010620/http:/www.lineto.com/ \"http://www.lineto.com\").\n\nRegards,  \nAS\n\n"
    },
    {
      "time": " 18.Oct.2005 10.56am",
      "content": "Thanks all.  \nFrank Rocholl, the designer of the site, was kind enough to answer by mail....  \nIts STORNO by Lineto. Bravo Alessandro!  \nIt keeps happening more and more. I am sitting on my huge and evergrowing forest of fonts.... cant see single trees anymore...getting older too : )\n\n"
    }
  ]
}
