{
  "id": "16101",
  "title": "Christmas Printer's Ornaments",
  "forum": "Home",
  "tags": [

  ],
  "content": "Submitted by [paul d hunt](http://web.archive.org/web/20071229230957/http:/www.typophile.com/user/7006 \"View user profile.\") : 7.Nov.2005 7.57am \n\n\\*+\\*+\\*+\\*+\\*+\\*+\\*+\\*+\\*+  \nSeasons Greetings!\n\nJust in time for holiday design projects, the Lanston  \nChristmas Ornaments collection has a definite nostalgic  \nand elegant feel for classic Christmas and Winter  \niconography. The set contains 5 fonts, including LTC  \nChristmas Ornaments and LTC Holly Leaves. Both are  \ndesigned to allow the user to create their own two-color  \ndesign combinations. An indispensable set for the  \nChristmas season, they are perfect for custom card  \ncreation or any other winter holiday graphics.\n\nThe set is available at 25% off until December 1st 2005 [http://www.p22.com/lanston/products/christmas.html](http://web.archive.org/web/20071229230957/http:/www.p22.com/lanston/products/christmas.html \"http://www.p22.com/lanston/products/christmas.html\")\n\n\\*+\\*+\\*+\\*+\\*+\\*+\\*+\\*+\\*+\\*+\\*+\\*+\\*+\\*+\\*+\\*+\\*+\\*+\\*  \nYule like this\n\nIn the spirit of the holiday themed fonts, we are also  \noffering the just released “Yule” set at 25% off as well.  \n($29.96 until Dec 1st 2005) [http://www.p22.com/ihof/yuleset.html](http://web.archive.org/web/20071229230957/http:/www.p22.com/ihof/yuleset.html \"http://www.p22.com/ihof/yuleset.html\")  \n(single Yule fonts are regular price)\n\n\\*+\\*+\\*+\\*+\\*+\\*+\\*+\\*+\\*+\\*+\\*+\\*+\\*+\\*+\\*+\\*+\\*+\\*+\\*  \nYou’ll love this\n\nOur holiday classic, the P22 snowflake font. It’s Free! [http://www.p22.com/free/snow.html](http://web.archive.org/web/20071229230957/http:/www.p22.com/free/snow.html \"http://www.p22.com/free/snow.html\")\n\n\\*+\\*+\\*+\\*+\\*+\\*+\\*+\\*+\\*+\\*+\\*+\\*+\\*+\\*+\\*+\\*+\\*+\\*+\\*  \nNew Catalog\n\nWe also have just received our 24 page 2006 type specimen  \nbooklets. Free for the asking... just fill out your  \nmailing information here: [http://www.p22.com/products/2006catalog.html](http://web.archive.org/web/20071229230957/http:/www.p22.com/products/2006catalog.html \"http://www.p22.com/products/2006catalog.html\")\n\n\\*+\\*+\\*+\\*+\\*+\\*+\\*+\\*+\\*+\\*+\\*+\\*+\\*+\\*+\\*+\\*+\\*+\\*+\\*\n\nHappy Holidays.  \nP22\n\n",
  "author": "<a href=\"http://web.archive.org/web/20071229230957/http:/www.typophile.com/user/7006\" title=\"View user profile.\">paul d hunt</a>",
  "time": ": 7.Nov.2005 7.57am",
  "uid": "7006",
  "comments": [

  ]
}
