{
  "id": "19312",
  "title": "(x) The Crown Valley Group, Inc. - Basilea {Eric Schmid}",
  "forum": "Type ID Board",
  "tags": [

  ],
  "content": "This looks familiar to me, but cannot pin it down. Anyone?\n\n ![](http://web.archive.org/web/20080605211051im_/http:/www.typophile.com/files/crown.jpg)\n\n [‹ Would Show the Extra Bold ornate serif face](http://web.archive.org/web/20080605211051/http:/www.typophile.com/node/19324 \"Go to previous forum topic\") [(x) Pampers website hand printed script - Andy Bold {Stephen} ›](http://web.archive.org/web/20080605211051/http:/www.typophile.com/node/19315 \"Go to next forum topic\")\n\n",
  "author": "<a href=\"/web/20080605211051/http://www.typophile.com/user/5948\" title=\"View user profile.\">evan</a>",
  "time": "<br>",
  "uid": "5948",
  "comments": [
    {
      "time": " 17.Apr.2006 2.23pm",
      "content": "[Friz Quadrata](http://web.archive.org/web/20080605211051/http:/www.fontshop.com/index.cfm?fuseaction=verity.search&searchstr=Friz%20Quadrata)\n\n"
    },
    {
      "time": " 17.Apr.2006 2.24pm",
      "content": "Hmm, maybe not. Or it’s just been mangled beyond recognition.\n\n"
    },
    {
      "time": " 17.Apr.2006 4.52pm",
      "content": "Maybe this will help\n\n ![](http://web.archive.org/web/20080605211051im_/http:/www.typophile.com/files/ms_crownvalley.jpg)\n\n"
    },
    {
      "time": " 17.Apr.2006 5.50pm",
      "content": "where did you find such a clean sample?\n\n"
    },
    {
      "time": " 17.Apr.2006 5.53pm",
      "content": "nevermind, looks like from the website, duh\n\n"
    },
    {
      "time": " 17.Apr.2006 9.24pm",
      "content": "Cannot find a link but I think it is Basilea - from maybe VGC and/or offered at one time by ImageClub. AFAIK\n\n"
    }
  ]
}
