{
  "id": "2012",
  "title": "ID Theft",
  "forum": "Release",
  "tags": [
    "Release"
  ],
  "content": "Here's a pretty sad example from the streets of LA:   \n [http://www.themicrofoundry.com/other/donuts.jpg](http://web.archive.org/web/20150414142119/http:/www.themicrofoundry.com/other/donuts.jpg)   \n   \n\"Anyone who would steal Souvenir would letterspace sheep... the pervert.\"   \n   \nhhp\n\n",
  "author": "hrant",
  "time": "10 Aug 2002 — 4:39pm",
  "uid": "1250",
  "comments": [
    {
      "time": "10 Aug 2002 — 8:53pm",
      "content": "The backward \"i\" is especially effective, as is the stunning way the type seems to \"dance\" across the sign.   \n   \n(There is no hope for humanity, is there?)   \n   \nDT\n\n"
    },
    {
      "time": "12 Aug 2002 — 1:03pm",
      "content": ":-)   \n   \nWhat that particular donut shop needs is the \\*font\\* police...   \n   \nhhp\n\n"
    },
    {
      "time": "13 Aug 2002 — 11:34am",
      "content": "This reminds me of those shops that open up in a former 7-Eleven space, and rename it to something like 7th Heaven- this way they only have to buy a few characters from the signmaker, who probably charges by the letter.\n\n"
    },
    {
      "time": "13 Aug 2002 — 12:46pm",
      "content": "Yeah, \"franchise parasites\": usually they just pay for the rights for a year, then once they have a customer base they save money by dumping the franchise and just changing some signs. Or sometimes not even: I remember a Tony Roma's on Cayman Islands that was no longer a Tony Roma's, except it still said so... And in Beirut there's \\*two\\* Hard Rock Cafes, but only one of them is the real thing - except you can't tell which!   \n   \nBTW, I think for Michelle's it was the donut cook who redid the signage...   \n   \nhhp\n\n"
    },
    {
      "time": "13 Aug 2002 — 3:03pm",
      "content": "\\>BTW, I think for Michelle's it was the donut cook who redid the signage...   \n   \nUsing letters made from donuts? ![:)](http://web.archive.org/web/20150414142119im_/http:/www.typophile.com/forums/clipart/happy.gif) (Actually, that might have looked better....)   \n   \nDT\n\n"
    },
    {
      "time": "12 Aug 2002 — 11:52am",
      "content": "So...what \\*is\\* that? An unitalics?\n\n"
    }
  ]
}
