{
  "id": "27807",
  "title": "any guesses",
  "forum": "Type ID Board",
  "tags": [

  ],
  "content": "Should know this one but can’t place it. Help\n\n| Attachment | Size |\n| --- | --- |\n| [old colony.jpg](http://web.archive.org/web/20081007185818/http:/typophile.com/files/old%20colony.jpg) | 181.35 KB |\n\n [‹ Changos](http://web.archive.org/web/20081007185818/http:/www.typophile.com/node/27820 \"Go to previous forum topic\") [Got another one for you guys :) ›](http://web.archive.org/web/20081007185818/http:/www.typophile.com/node/27747 \"Go to next forum topic\")\n\n",
  "author": "<a href=\"/web/20081007185818/http://www.typophile.com/user/11558\" title=\"View user profile.\">drax911sc</a>",
  "time": "<br>",
  "uid": "11558",
  "comments": [
    {
      "time": " 21.Aug.2006 10.18am",
      "content": "I think it’s [Kaufmann Bold](http://web.archive.org/web/20081007185818/http:/www.fontshop.com/index.cfm?fuseaction=catalog.fontdetail&displayfontid=BT.122374.0.0&attributes.sampleSize=48&sampleText=Old+Colony&sampleSize=48)\n\n"
    },
    {
      "time": " 21.Aug.2006 12.56pm",
      "content": "Thanks a bunch. Right on the money.\n\n"
    }
  ]
}
