{
  "id": "4129",
  "title": "(x) Attn: Mike Y --\\> Fudge font? - Boca Raton (customized) {Mike F}",
  "forum": "Type ID Board",
  "tags": [

  ],
  "content": "Well spotted... That sure looks like an ID to me...\n\n",
  "author": "nicolai",
  "time": "Mon, 2004-04-05 14:57",
  "uid": "669",
  "comments": [
    {
      "time": " Mon, 2004-04-05 16:28",
      "content": "Nice job Mike! If I turn the g upside down I have the d. The only thing left would be smoothing the terminals on them.   \n   \nI have that collection too, so I should lose points for not recognizing it.   \n   \nThanks.\n\n"
    }
  ]
}
