{
  "id": "4132",
  "title": "(x) Esquire Magazine Sans - Crank 8 {BJ}",
  "forum": "Type ID Board",
  "tags": [

  ],
  "content": "I picked up a copy of Esquire Magazine (which I don't normally read) this month and am smitten with the san they use throughout. Can anyone tell me what it is (or if it's even available)? Here's the cover -- it's all over it (the one used in \"The Naked Truth About Women\", for example).   \n   \nThanks in advance! ![Esquire 042004](http://web.archive.org/web/20120102172026im_/http:/www.typophile.com/forums/messages/83/32703.jpg)\n\n",
  "author": "<a href=\"/web/20120102172026/http://typophile.com/user/2743\" title=\"View user profile.\">jcroft</a>",
  "time": "<br>",
  "uid": "2743",
  "comments": [
    {
      "time": "",
      "content": "FWIW, I think the W, K, and w are probably the characters that should give this one away! ![:-)](http://web.archive.org/web/20120102172026im_/http:/www.typophile.com/forums/clipart/happy.gif)\n\n"
    },
    {
      "time": "",
      "content": "Fabio was asking me about this font the other day... we got nowhere. He was smitten by the font and the woman, too.\n\n"
    },
    {
      "time": "",
      "content": "The woman is great, but the font is even better. Wait, what does that say about me? ![:-)](http://web.archive.org/web/20120102172026im_/http:/www.typophile.com/forums/clipart/happy.gif)   \n   \nThe uppercase U is also pretty distinctive...   \n   \nJeff\n\n"
    },
    {
      "time": "",
      "content": "I'm sorry, did someone say there was type on this cover? Where is it? All I see is Rachel Weisz and a snake.\n\n"
    },
    {
      "time": "",
      "content": "Damnit Dave -- I was counting on you! ![:-)](http://web.archive.org/web/20120102172026im_/http:/www.typophile.com/forums/clipart/happy.gif)\n\n"
    },
    {
      "time": "",
      "content": "Ole first mentioned this typeface in the Oban thread, iirc.   \n   \ni believe it's Crank 8 designed by Henk Elenga and Greg Lindy\n\n"
    },
    {
      "time": "",
      "content": "I tried both Identifont.com and WhatTheFont with no luck. ![:-(](http://web.archive.org/web/20120102172026im_/http:/www.typophile.com/forums/clipart/sad.gif)\n\n"
    },
    {
      "time": "",
      "content": "I wish I could help, but, you know, I'm just on my way out the door. Gotta run an errand near a magazine stand...\n\n"
    },
    {
      "time": "",
      "content": "I think you nailed it, BJ. Damn, I was hoping it'd be more readily available. Ah well.   \n   \nThanks!   \n   \nJeff\n\n"
    },
    {
      "time": "",
      "content": "What an excellent ID, BJ!\n\n"
    },
    {
      "time": "",
      "content": "Crank 8. I bought a book about Henk Elenga a year ago which was it's first use. I believe is is about $100 from instersection studios. At the time there was of course no mention of typeface   \ndesigner nor source. When Greg Lindy first surfaced (in my serach) it was with his font releases with Thirstype. I bought Section which is also quite nice.   \n   \nSample from book   \n   \n ![henk](http://web.archive.org/web/20120102172026im_/http:/www.typophile.com/forums/messages/83/32718.jpg)\n\n"
    },
    {
      "time": "",
      "content": "[http://www.intersectionstudio.com/](http://web.archive.org/web/20120102172026/http:/www.intersectionstudio.com/)\n\n"
    }
  ]
}
