{
  "id": "43009",
  "title": "Slab Serif Typeface?",
  "forum": "Type ID Board",
  "tags": [

  ],
  "content": "I would appreciate any help figuring out what this slab serif is. It looks a bit dated, and seems close to a lot of things I have been looking at, but I can’t nail it down.\n\nThanks so much,\n\nJarrod\n\n| Attachment | Size |\n| --- | --- |\n| [Johnny\\_Cash.jpg](http://web.archive.org/web/20080312105130/http:/typophile.com/files/Johnny_Cash.jpg) | 28 KB |\n\n [‹ Strange f serifs](http://web.archive.org/web/20080312105130/http:/typophile.com/node/43012 \"Go to previous forum topic\") [Srcript font in a vinegar label ›](http://web.archive.org/web/20080312105130/http:/typophile.com/node/42997 \"Go to next forum topic\")\n\n",
  "author": "<a href=\"/web/20080312105130/http://typophile.com/user/17234\" title=\"View user profile.\">jmryhal</a>",
  "time": "<br>",
  "uid": "17234",
  "comments": [
    {
      "time": " 10.Mar.2008 1.10pm",
      "content": "[Giza](http://web.archive.org/web/20080312105130/http:/www.fontshop.com/fonts/singles/font_bureau/giza_seven_three/?sample_text=JOHNNY%20CASH&sample_size=48)\n\n"
    },
    {
      "time": " 10.Mar.2008 1.12pm",
      "content": "FB Giza\n\n[http://www.fontbureau.com/fonts/Giza](http://web.archive.org/web/20080312105130/http:/www.fontbureau.com/fonts/Giza \"http://www.fontbureau.com/fonts/Giza\")\n\n"
    },
    {
      "time": " 10.Mar.2008 1.13pm",
      "content": "I am SuperUltraLate.\n\n"
    },
    {
      "time": " 10.Mar.2008 1.14pm",
      "content": "But you are so exceedingly cool (cough, cough)\n\nMikey :-)\n\n"
    }
  ]
}
