{
  "id": "44774",
  "title": "help me",
  "forum": "Hiroshige's blog",
  "tags": [

  ],
  "content": " ![](http://web.archive.org/web/20131023164714im_/http:/typophile.com/files/help_me_3579.jpg)\n\n",
  "author": "Hiroshige",
  "time": "28 Apr 2008 — 10:57pm",
  "uid": "9690",
  "comments": [
    {
      "time": "28 Apr 2008 — 11:01pm",
      "content": "Black on black, vine of thorns, bold text - help me - is a dark statement of despair, a desperate effort to be heard on a personal\\* level in raw terms.\n\n\\*Personal, refering to the viewer.\n\n"
    }
  ]
}
