{
  "id": "46148",
  "title": "70s Serif-ish",
  "forum": "Type ID Board",
  "tags": [

  ],
  "content": "Thanks for any help....\n\n ![](http://web.archive.org/web/20080609010902im_/http:/typophile.com/files/70s_Serif_3642.jpg)\n\n [‹ Anybody know this font.](http://web.archive.org/web/20080609010902/http:/typophile.com/node/46163 \"Go to previous forum topic\") [any help much appreciated... ›](http://web.archive.org/web/20080609010902/http:/typophile.com/node/46157 \"Go to next forum topic\")\n\n",
  "author": "<a href=\"/web/20080609010902/http://typophile.com/user/9177\" title=\"View user profile.\">BrooklynRob</a>",
  "time": "<br>",
  "uid": "9177",
  "comments": [
    {
      "time": " 6.Jun.2008 7.26am",
      "content": "..\n\n"
    },
    {
      "time": " 6.Jun.2008 4.01pm",
      "content": "Similar to ITC Elan. It may be custom since it’s a logo.\n\n- Lex\n\n"
    }
  ]
}
