{
  "id": "48811",
  "title": "(x) \"Relax · Enjoy\" Bauhaus-like geometric sans - Rezland {Rainer}",
  "forum": "Type ID Board",
  "tags": [

  ],
  "content": "Can someone please ID this..... its killing me\n\n| Attachment | Size |\n| --- | --- |\n| [Picture-1.jpg](http://web.archive.org/web/20081201180205/http:/typophile.com/files/Picture-1_5.jpg) | 7.03 KB |\n\n [‹ (x) Cute slab serif in \"Thesis\" WordPress Theme- PMN Caecilia {Jan E}](http://web.archive.org/web/20081201180205/http:/www.typophile.com/node/48890 \"Go to previous forum topic\") [(x) Script logo on \"Mensch ärgere Dich nicht\" board game - (similar to) Sterling Script {Mike Y} ›](http://web.archive.org/web/20081201180205/http:/www.typophile.com/node/48889 \"Go to next forum topic\")\n\n",
  "author": "<a href=\"/web/20081201180205/http://www.typophile.com/user/8234\" title=\"View user profile.\">dontbugme</a>",
  "time": "<br>",
  "uid": "8234",
  "comments": [
    {
      "time": " 26.Aug.2008 5.55pm",
      "content": "[Rezland](http://web.archive.org/) by Fraser Davidson.\n\n"
    },
    {
      "time": " 27.Aug.2008 3.13pm",
      "content": "Sweet! Thanks!\n\n"
    },
    {
      "time": " 27.Aug.2008 3.30pm",
      "content": "You are welcome, Susan.\n\n"
    },
    {
      "time": " 28.Aug.2008 11.42am",
      "content": "Are we cutting off links to Dafont now? Renko’s link wouldn’t work when I tried to see the font.\n\n- Mike Yanega\n\n"
    },
    {
      "time": " 28.Aug.2008 11.46am",
      "content": "No, Mike, I don’t think we do. I guess Renko just messed up his formatting.\n\n"
    },
    {
      "time": " 28.Aug.2008 1.09pm",
      "content": "No we aren’t killing links for Dafont.\n\n"
    },
    {
      "time": " 28.Aug.2008 2.22pm",
      "content": "Sorry, Mike. Yes, I messed up my link but won’t fix it, because of the right timestamp. (Besides I am not allowed to edit in this timestage). But clicking the messedlink with the right mouseclick leads to a pulldownmenu with google and the first result is thr link to dafont so I didn’t mind. Sorry for the confusion.\n\n"
    }
  ]
}
