{
  "id": "50144",
  "title": "Hello Pocatello, anyone know this font?",
  "forum": "Type ID Board",
  "tags": [

  ],
  "content": " ![](http://web.archive.org/web/20081009110241im_/http:/typophile.com/files/lies-font_5601.gif)\n\nIt can also be seen on the Brass Tacks Design website, I have been trying to figure out what font it is and is driving me crazy.\n\nAny input would be helpful.\n\nCheers.\n\n [‹ Capitolium?](http://web.archive.org/web/20081009110241/http:/typophile.com/node/50156 \"Go to previous forum topic\") [puls tv ›](http://web.archive.org/web/20081009110241/http:/typophile.com/node/50151 \"Go to next forum topic\")\n\n",
  "author": "<a href=\"/web/20081009110241/http://typophile.com/user/37664\" title=\"View user profile.\">jim_</a>",
  "time": "<br>",
  "uid": "37664",
  "comments": [
    {
      "time": " 3.Oct.2008 7.14pm",
      "content": "It might be one of HTF’s [Knockout](http://web.archive.org/web/20081009110241/http:/www.typography.com/fonts/font_styles.php?productLineID=100013) variations.\n\n"
    },
    {
      "time": " 3.Oct.2008 7.31pm",
      "content": "or Font Bureau’s [Titling Gothic Skyline](http://web.archive.org/web/20081009110241/http:/www.fontbureau.com/newspaper/fonts/TitlingGothicFB/styles)\n\n"
    },
    {
      "time": " 3.Oct.2008 8.51pm",
      "content": "Thank you Vivicity for the prompt reply. I also thought at first that it could be Knockout variations, but if you look closer there are differences on the “R” and a few other characters. However, you may be right, Titling Gothic highly resembles most, if not all, characters.\n\nMany thanks!\n\n"
    },
    {
      "time": " 3.Oct.2008 10.01pm",
      "content": "Could this be the same font as that Feltron annual report (Opti Giant I think)?\n\n- Lex\n\n"
    },
    {
      "time": " 3.Oct.2008 10.21pm",
      "content": "Nah, Giant has a different ’G’ and circular punctuation among other things.\n\n- Lex\n\n"
    },
    {
      "time": " 4.Oct.2008 3.43pm",
      "content": "Hey Lex,\n\nThey look pretty similar also, but you’re right, there are some small differences.\n\nSo far, Titling seems to resemble it the most, I hope it is for the sake of my sanity!\n\nCheers.\n\n"
    }
  ]
}
