{
  "id": "56198",
  "title": "Type ID for $",
  "forum": "Type ID Board",
  "tags": [

  ],
  "content": "I am working on a research project and need someone to do vast amounts of type identification.  \nIf interested, Contact me: [sberlow@fontbureau.com](mailto:sberlow@fontbureau.com).\n\n [‹ Donne Angular Latin ID](http://web.archive.org/web/20090327142452/http:/typophile.com/node/56156 \"Go to previous forum topic\") [ID on unknown modern Frutiger Next-like sans serif ›](http://web.archive.org/web/20090327142452/http:/typophile.com/node/56158 \"Go to next forum topic\")\n\n",
  "author": "<a href=\"/web/20090327142452/http://typophile.com/user/1994\" title=\"View user profile.\">sberlow</a>",
  "time": "<br>",
  "uid": "1994",
  "comments": [

  ]
}
