{
  "id": "65215",
  "title": "(x) Saks 5th Ave - custom by Tom Carnase/Joe Finocchiaro {Riccardo}",
  "forum": "Type ID Board",
  "tags": [

  ],
  "content": "Hi all.\n\nJust a real quick question...does anyone know the font (or similar font) to the Saks 5th Ave brand??\n\n[http://www.brandsoftheworld.com/search/114661098/19954.html](http://web.archive.org/web/20100202112720/http:/www.brandsoftheworld.com/search/114661098/19954.html)\n\n",
  "author": "<a href=\"/web/20100202112720/http://typophile.com/user/35693\" title=\"View user profile.\">luccio</a>",
  "time": "<br>",
  "uid": "35693",
  "comments": [
    {
      "time": "",
      "content": "[http://typophile.com/node/30474](http://web.archive.org/web/20100202112720/http:/typophile.com/node/30474 \"http://typophile.com/node/30474\")  \n [http://typophile.com/node/31424](http://web.archive.org/web/20100202112720/http:/typophile.com/node/31424 \"http://typophile.com/node/31424\")  \n [http://typophile.com/search/?keys=saks%20fifth%20avenue](http://web.archive.org/web/20100202112720/http:/typophile.com/search/?keys=saks%20fifth%20avenue \"http://typophile.com/search/?keys=saks%20fifth%20avenue\")  \n [http://www.joefino.com/Pages\\_3/L05.html](http://web.archive.org/web/20100202112720/http:/www.joefino.com/Pages_3/L05.html \"http://www.joefino.com/Pages\\_3/L05.html\")\n\n"
    }
  ]
}
