{
  "id": "65831",
  "title": "Gothic lowercase \"a\"",
  "forum": "Type ID Board",
  "tags": [

  ],
  "content": "I've received no replies on the What the Font forum, so I've decided to try here. This typeface looks very familiar to me, but for the life of me I just cannot identify it on my own. Do any of you have any ideas as to what its name is?\n\n| Attachment | Size |\n| --- | --- |\n| [a.jpg](http://web.archive.org/web/20100202051027/http:/typophile.com/files/a_44.jpg) | 38.52 KB |\n\n",
  "author": "<a href=\"/web/20100202051027/http://typophile.com/user/51908\" title=\"View user profile.\">Frans</a>",
  "time": "<br>",
  "uid": "51908",
  "comments": [
    {
      "time": "",
      "content": "Where did you find this sample?\n\n"
    },
    {
      "time": "",
      "content": "In a book called \"The Vampire Companion: The Official Guide to Anne Rice's The Vampire Chronicles\" by Katherine Ramsland. It was published by Ballantine Books in 1993 and revised in 1995. This sample comes from the revised edition.\n\n"
    },
    {
      "time": "",
      "content": "I can add that the book also uses various weights of Galliard, Footlight, and Goudy Old Style, among a few other fonts I am too lazy to remember at the moment. Lol.\n\n"
    },
    {
      "time": "",
      "content": "Close: [http://new.myfonts.com/fonts/sentinel/sibyl/](http://web.archive.org/web/20100202051027/http:/new.myfonts.com/fonts/sentinel/sibyl/ \"http://new.myfonts.com/fonts/sentinel/sibyl/\")  \nDon't forget to check the alts.\n\nhhp\n\n"
    },
    {
      "time": "",
      "content": "[Journalistic](http://web.archive.org/web/20100202051027/http:/new.myfonts.com/fonts/ephemera/journalistic/?testdrive=dock%3Dfalse%26size%3D221%26w%3D600%26src%3Dcustom%26text%3Da%26fg%3D000000%26bg%3Dffffff%26goodies%3Dot.liga%26seed%3D29) and [Archive Copperplate Text](http://web.archive.org/web/20100202051027/http:/new.myfonts.com/fonts/archivetype/archive-copperplate-text/?testdrive=dock%3Dfalse%26size%3D221%26w%3D600%26src%3Dcustom%26text%3Da%26fg%3D000000%26bg%3Dffffff%26goodies%3Dot.liga%26seed%3D44) are roughed up versions of the character. Which, you know, doesn't help, but is interesting. :)\n\n"
    },
    {
      "time": "",
      "content": "Thanks for the suggestion, hrant, but Sibyl isn't what I'm looking for. Its lowercase \"a\" is single storey unlike the one in the image I uploaded.\n\n"
    },
    {
      "time": "",
      "content": "Very interesting, Stephen. Thanks. :)\n\n"
    }
  ]
}
