{
  "id": "6730",
  "title": "(x) Pearl Moon Boutique - Futura {Yves}",
  "forum": "Type ID Board",
  "tags": [

  ],
  "content": "Last one for now..   \n   \nLooks like a font for a boutique/salon. Really skinny.. clean design   \n   \n ![Skinny clean boutique font](http://web.archive.org/web/20081121091051im_/http:/www.typophile.com/forums/messages/83/49236.jpg)\n\n [‹ &#40;x&#41; The Crown Publishing Group - Mrs. Eaves {Massimo Nardini &#40;self&#41;}](http://web.archive.org/web/20081121091051/http:/www.typophile.com/node/6731 \"Go to previous forum topic\") [Pr ›](http://web.archive.org/web/20081121091051/http:/www.typophile.com/node/6728 \"Go to next forum topic\")\n\n",
  "author": "<a href=\"/web/20081121091051/http://www.typophile.com/user/4683\" title=\"View user profile.\">arcanegel</a>",
  "time": "<br>",
  "uid": "4683",
  "comments": [
    {
      "time": " 18.Sep.2004 10.20am",
      "content": "Isn't that plain old [Futura](http://web.archive.org/web/20081121091051/http:/www.myfonts.com/fonts/neufville/futura-nd/light/testdrive.html?s=PEARL%20MOON%20BOUTIQUE&p=36)?\n\n"
    },
    {
      "time": " 18.Sep.2004 11.48am",
      "content": "Yves:   \n   \nWell.. yeah.. of course.. I mean.. I saw it immediately and everything.. I was just testing the skills..   \n   \n... i'll shut up now.   \n   \nFor someone who's just getting in this.. you guys are just amazing. As soon as I sort out the paypal thing.. consider me a member..   \n   \nor rather a fan.   \n   \nThanks again.   \nrc\n\n"
    },
    {
      "time": " 18.Sep.2004 12.48pm",
      "content": "Hehe, Rafael, I didn't mean it that way, I was just \"talking to   \nmyself\" out loud. Should've added a smiley ![:-)](http://web.archive.org/web/20081121091051im_/http:/www.typophile.com/forums/clipart/happy.gif) Glad I could   \nhelp you out.\n\n"
    }
  ]
}
